{"nodes": [{"id": "c_users_super_afflowv2_app_lib_fraud_server_ts", "label": "fraud.server.ts", "file_type": "code", "source_file": "C:\\Users\\super\\AfflowV2\\app\\lib\\fraud.server.ts", "source_location": "L1"}, {"id": "fraud_server_checkselfreferral", "label": "checkSelfReferral()", "file_type": "code", "source_file": "C:\\Users\\super\\AfflowV2\\app\\lib\\fraud.server.ts", "source_location": "L23"}, {"id": "fraud_server_checkconversionrate", "label": "checkConversionRate()", "file_type": "code", "source_file": "C:\\Users\\super\\AfflowV2\\app\\lib\\fraud.server.ts", "source_location": "L46"}, {"id": "fraud_server_checkrapidorders", "label": "checkRapidOrders()", "file_type": "code", "source_file": "C:\\Users\\super\\AfflowV2\\app\\lib\\fraud.server.ts", "source_location": "L81"}, {"id": "fraud_server_runfraudchecks", "label": "runFraudChecks()", "file_type": "code", "source_file": "C:\\Users\\super\\AfflowV2\\app\\lib\\fraud.server.ts", "source_location": "L111"}, {"id": "fraud_server_flagaffiliate", "label": "flagAffiliate()", "file_type": "code", "source_file": "C:\\Users\\super\\AfflowV2\\app\\lib\\fraud.server.ts", "source_location": "L140"}], "edges": [{"source": "c_users_super_afflowv2_app_lib_fraud_server_ts", "target": "c_users_super_afflowv2_app_db_server", "relation": "imports_from", "confidence": "EXTRACTED", "source_file": "C:\\Users\\super\\AfflowV2\\app\\lib\\fraud.server.ts", "source_location": "L11", "weight": 1.0}, {"source": "c_users_super_afflowv2_app_lib_fraud_server_ts", "target": "fraud_server_checkselfreferral", "relation": "contains", "confidence": "EXTRACTED", "source_file": "C:\\Users\\super\\AfflowV2\\app\\lib\\fraud.server.ts", "source_location": "L23", "weight": 1.0}, {"source": "c_users_super_afflowv2_app_lib_fraud_server_ts", "target": "fraud_server_checkconversionrate", "relation": "contains", "confidence": "EXTRACTED", "source_file": "C:\\Users\\super\\AfflowV2\\app\\lib\\fraud.server.ts", "source_location": "L46", "weight": 1.0}, {"source": "c_users_super_afflowv2_app_lib_fraud_server_ts", "target": "fraud_server_checkrapidorders", "relation": "contains", "confidence": "EXTRACTED", "source_file": "C:\\Users\\super\\AfflowV2\\app\\lib\\fraud.server.ts", "source_location": "L81", "weight": 1.0}, {"source": "c_users_super_afflowv2_app_lib_fraud_server_ts", "target": "fraud_server_runfraudchecks", "relation": "contains", "confidence": "EXTRACTED", "source_file": "C:\\Users\\super\\AfflowV2\\app\\lib\\fraud.server.ts", "source_location": "L111", "weight": 1.0}, {"source": "c_users_super_afflowv2_app_lib_fraud_server_ts", "target": "fraud_server_flagaffiliate", "relation": "contains", "confidence": "EXTRACTED", "source_file": "C:\\Users\\super\\AfflowV2\\app\\lib\\fraud.server.ts", "source_location": "L140", "weight": 1.0}, {"source": "fraud_server_runfraudchecks", "target": "fraud_server_checkselfreferral", "relation": "calls", "confidence": "EXTRACTED", "source_file": "C:\\Users\\super\\AfflowV2\\app\\lib\\fraud.server.ts", "source_location": "L117", "weight": 1.0}, {"source": "fraud_server_runfraudchecks", "target": "fraud_server_checkconversionrate", "relation": "calls", "confidence": "EXTRACTED", "source_file": "C:\\Users\\super\\AfflowV2\\app\\lib\\fraud.server.ts", "source_location": "L118", "weight": 1.0}, {"source": "fraud_server_runfraudchecks", "target": "fraud_server_checkrapidorders", "relation": "calls", "confidence": "EXTRACTED", "source_file": "C:\\Users\\super\\AfflowV2\\app\\lib\\fraud.server.ts", "source_location": "L119", "weight": 1.0}], "raw_calls": [{"caller_nid": "fraud_server_checkselfreferral", "callee": "toLowerCase", "source_file": "C:\\Users\\super\\AfflowV2\\app\\lib\\fraud.server.ts", "source_location": "L31"}, {"caller_nid": "fraud_server_checkselfreferral", "callee": "toLowerCase", "source_file": "C:\\Users\\super\\AfflowV2\\app\\lib\\fraud.server.ts", "source_location": "L31"}, {"caller_nid": "fraud_server_checkconversionrate", "callee": "findUnique", "source_file": "C:\\Users\\super\\AfflowV2\\app\\lib\\fraud.server.ts", "source_location": "L49"}, {"caller_nid": "fraud_server_checkconversionrate", "callee": "count", "source_file": "C:\\Users\\super\\AfflowV2\\app\\lib\\fraud.server.ts", "source_location": "L58"}, {"caller_nid": "fraud_server_checkconversionrate", "callee": "toFixed", "source_file": "C:\\Users\\super\\AfflowV2\\app\\lib\\fraud.server.ts", "source_location": "L69"}, {"caller_nid": "fraud_server_checkrapidorders", "callee": "now", "source_file": "C:\\Users\\super\\AfflowV2\\app\\lib\\fraud.server.ts", "source_location": "L86"}, {"caller_nid": "fraud_server_checkrapidorders", "callee": "count", "source_file": "C:\\Users\\super\\AfflowV2\\app\\lib\\fraud.server.ts", "source_location": "L88"}, {"caller_nid": "fraud_server_runfraudchecks", "callee": "all", "source_file": "C:\\Users\\super\\AfflowV2\\app\\lib\\fraud.server.ts", "source_location": "L116"}, {"caller_nid": "fraud_server_runfraudchecks", "callee": "flatMap", "source_file": "C:\\Users\\super\\AfflowV2\\app\\lib\\fraud.server.ts", "source_location": "L122"}, {"caller_nid": "fraud_server_runfraudchecks", "callee": "some", "source_file": "C:\\Users\\super\\AfflowV2\\app\\lib\\fraud.server.ts", "source_location": "L123"}, {"caller_nid": "fraud_server_runfraudchecks", "callee": "some", "source_file": "C:\\Users\\super\\AfflowV2\\app\\lib\\fraud.server.ts", "source_location": "L124"}, {"caller_nid": "fraud_server_runfraudchecks", "callee": "some", "source_file": "C:\\Users\\super\\AfflowV2\\app\\lib\\fraud.server.ts", "source_location": "L126"}, {"caller_nid": "fraud_server_flagaffiliate", "callee": "update", "source_file": "C:\\Users\\super\\AfflowV2\\app\\lib\\fraud.server.ts", "source_location": "L144"}, {"caller_nid": "fraud_server_flagaffiliate", "callee": "warn", "source_file": "C:\\Users\\super\\AfflowV2\\app\\lib\\fraud.server.ts", "source_location": "L148"}]}